odoo/addons/stock_mts_mto_rule/README.rst
odoo/addons/stock_mts_mto_rule/__init__.py
odoo/addons/stock_mts_mto_rule/__manifest__.py
odoo/addons/stock_mts_mto_rule/data/stock_data.xml
odoo/addons/stock_mts_mto_rule/i18n/cs_CZ.po
odoo/addons/stock_mts_mto_rule/i18n/de.po
odoo/addons/stock_mts_mto_rule/i18n/es.po
odoo/addons/stock_mts_mto_rule/i18n/es_MX.po
odoo/addons/stock_mts_mto_rule/i18n/fr.po
odoo/addons/stock_mts_mto_rule/i18n/fr_FR.po
odoo/addons/stock_mts_mto_rule/i18n/hr.po
odoo/addons/stock_mts_mto_rule/i18n/it.po
odoo/addons/stock_mts_mto_rule/i18n/nl.po
odoo/addons/stock_mts_mto_rule/i18n/nl_NL.po
odoo/addons/stock_mts_mto_rule/i18n/pt_BR.po
odoo/addons/stock_mts_mto_rule/i18n/pt_PT.po
odoo/addons/stock_mts_mto_rule/i18n/ro.po
odoo/addons/stock_mts_mto_rule/i18n/sk.po
odoo/addons/stock_mts_mto_rule/i18n/sl.po
odoo/addons/stock_mts_mto_rule/i18n/stock_mts_mto_rule.pot
odoo/addons/stock_mts_mto_rule/i18n/tr_TR.po
odoo/addons/stock_mts_mto_rule/i18n/vi_VN.po
odoo/addons/stock_mts_mto_rule/i18n/zh_CN.po
odoo/addons/stock_mts_mto_rule/models/__init__.py
odoo/addons/stock_mts_mto_rule/models/stock_rule.py
odoo/addons/stock_mts_mto_rule/models/stock_warehouse.py
odoo/addons/stock_mts_mto_rule/readme/CONFIGURE.rst
odoo/addons/stock_mts_mto_rule/readme/CONTRIBUTORS.rst
odoo/addons/stock_mts_mto_rule/readme/DESCRIPTION.rst
odoo/addons/stock_mts_mto_rule/readme/ROADMAP.rst
odoo/addons/stock_mts_mto_rule/readme/USAGE.rst
odoo/addons/stock_mts_mto_rule/static/description/icon.png
odoo/addons/stock_mts_mto_rule/static/description/index.html
odoo/addons/stock_mts_mto_rule/tests/__init__.py
odoo/addons/stock_mts_mto_rule/tests/test_mto_mts_route.py
odoo/addons/stock_mts_mto_rule/view/pull_rule.xml
odoo/addons/stock_mts_mto_rule/view/warehouse.xml
odoo12_addon_stock_mts_mto_rule-12.0.1.0.2.dist-info/METADATA
odoo12_addon_stock_mts_mto_rule-12.0.1.0.2.dist-info/WHEEL
odoo12_addon_stock_mts_mto_rule-12.0.1.0.2.dist-info/top_level.txt
odoo12_addon_stock_mts_mto_rule-12.0.1.0.2.dist-info/RECORD
